Verilog_Folder/CPU/ALU.v
module ALU (
	input wire [15 : 0] inDataA, inDataB,
	input wire [3 : 0] aluCode,
	output reg [15 : 0] aluData,
	output reg ifBan
);

	initial begin
		ifBan = 0;
		aluData = 0;
	end

	always @* begin
		if (ifBan == 1) begin
			#2
			ifBan = ~ifBan;
		end
	end

	always @* begin
		case (aluCode)
			4'b0000: aluData = 0;
			4'b0001: aluData = ~inDataA;
			4'b0010: aluData = (inDataA >>> 1);
			4'b0011: aluData = {inDataA[14 : 0], inDataA[15]};
			4'b0100: aluData = inDataA + inDataB;
			4'b0101: aluData = inDataA;
			4'b0110: aluData = inDataB;
			4'b0111: ifBan = inDataA[15] == 1 ? 1 : 0;
		endcase
	end
endmodule

Verilog_Folder/CPU/CTRLUNIT.v
module CTRLUNIT (
	input wire [3 : 0] insLong,
	input wire [2 : 0] insShort,
	input wire insMode,
	output reg stop, pcWR, accWR, memWR,
	output reg [3 : 0] aluCode
);

	initial begin
		stop = 0;
		pcWR = 0;
		accWR = 0;
		memWR = 0;
		aluCode = 4'bX;
	end

	always @(insMode, insShort, insLong) begin
		if (insMode == 0) begin
			case (insShort)
				3'b001: {stop, pcWR, accWR, memWR, aluCode} = 8'b00010101;	//001	sta
				3'b010: {stop, pcWR, accWR, memWR, aluCode} = 8'b00100110;	//010	lda
				3'b011: {stop, pcWR, accWR, memWR, aluCode} = 8'b00100000;	//011	cla
				3'b100: {stop, pcWR, accWR, memWR, aluCode} = 8'b00100001;	//100	com
				3'b101: {stop, pcWR, accWR, memWR, aluCode} = 8'b01001111;	//101	jmp
			endcase
		end else begin
			case (insLong)
				4'b1000: {stop, pcWR, accWR, memWR, aluCode} = 8'b00100100;	//1000	add
				4'b1100: {stop, pcWR, accWR, memWR, aluCode} = 8'b01000111;	//1100	ban
				4'b1101: {stop, pcWR, accWR, memWR, aluCode} = 8'b00100010;	//1101	shr
				4'b1110: {stop, pcWR, accWR, memWR, aluCode} = 8'b00100011;	//1110	csl
				4'b1111: {stop, pcWR, accWR, memWR, aluCode} = 8'b10101111;	//1111	stp
			endcase
		end
	end

endmodule

Verilog_Folder/CPU/MEMOR.v
module MEMOR (
	input memWR, clk,
	input wire [7 : 0] dataAddr,
	input wire [15 : 0] inData,
	output wire [15 : 0] outData
);

	reg [15 : 0] unit [8'b11111111 : 0];

	assign outData = unit[dataAddr];

	initial begin
		unit[0] = 16'h0002;
		unit[1] = 16'h0030;
		unit[2] = 16'h000F;
		unit[11] = 16'hFFE1;
	end

	always @(negedge clk) begin
		if (memWR == 1)
			unit[dataAddr] = inData;
	end
endmodule

Verilog_Folder/CPU/ACC.v
module ACC (
	input wire clk, accWR,
	input wire [15 : 0] inData,
	output wire [15 : 0] outData
);

	reg [15 : 0] accData;

	assign outData = accData;

	initial begin
		accData = 0;
	end

	always @(negedge clk) begin
		if (accWR == 1)
			accData = inData;
	end

endmodule

Verilog_Folder/CPU/INSREG.v
module INSREG (
	input wire [7 : 0] Addr,
	output reg [3 : 0] insLong,
	output reg [2 : 0] insShort,
	output reg insMode,
	output reg [7 : 0] dataAddr
);

	reg [11 : 0] unit[8'b11111111:0];
	reg [11 : 0] ins;

	initial begin
		unit[0] = 11'b01000000001;		// lda
		unit[1] = 12'b100000000010;		// add
		unit[2] = 4'b1110;				// csl
		unit[3] = 4'b1101;				// shr
		unit[4] = 3'b100;				// com
		unit[5] = 3'b011;				// cla
		unit[6] = 11'b01000000010;		// lda
		unit[7] = 4'b1110;				// csl
		unit[8] = 12'b100000001011;		// add
		unit[9] = 11'b00100000010;		// sta
		unit[10] = 12'b110000000010;	// ban
		unit[11] = 12'b100000001011;	// add
		unit[12] = 11'b10100001110;		// jmp
		unit[13] = 12'b100000001011;	// add
		unit[14] = 4'b1111;				// stp
	end

	always @* begin
		ins = unit[Addr];
		if (ins[11 : 9] == 0) begin
			if (ins[8] == 0) begin
				if (ins[3] == 0) begin
					{insMode, insShort, insLong, dataAddr} = {1'b0, ins[2 : 0], 4'b0000, 8'b00000000};	// cla com
				end else begin
					{insMode, insShort, insLong, dataAddr} = {1'b1, 3'b000, ins[3 : 0], 8'b00000000};	// csl shr stp
				end
			end else begin
				{insMode, insShort, insLong, dataAddr} = {1'b0, ins[10 : 8], 4'b0000, ins[7 : 0]};		// sta
			end
		end else begin
			if (ins[11] == 0) begin
				{insMode, insShort, insLong, dataAddr} = {1'b0, ins[10 : 8], 4'b0000, ins[7 : 0]};		// lda jmp
			end else begin
				{insMode, insShort, insLong, dataAddr} = {1'b1, 3'b000, ins[11 : 8], ins[7 : 0]};		// ban add
			end
		end
	end

endmodule

Verilog_Folder/CPU/PC.v
module PC (
	input wire clk, rst, stop, pcWR, ifBan,
	input wire [7 : 0] jump,
	output reg [7 : 0] Addr
);

	initial begin
		Addr = 0;
	end

	always @* begin
		if (stop == 0) begin
			if (rst == 1) begin
				Addr = 0;
			end
		end
	end

	always @(posedge clk) begin
		if (stop == 0) begin
			Addr = Addr + 1;
		end
	end

	always @(negedge clk) begin
		if (stop == 0) begin
			if (pcWR == 1) begin
				if (ifBan == 0) begin
					Addr = jump - 1;
				end else begin
					Addr = Addr + jump - 1;
				end
			end
		end
	end
	
endmodule

Verilog_Folder/CPU/CPU.v
`include "PC.v"
`include "INSREG.v"
`include "ACC.v"
`include "MEMOR.v"
`include "CTRLUNIT.v"
`include "ALU.v"

module CPU (
	input wire clk, rst
);

	wire stop, pcWR, accWR, memWR, insMode, ifBan;
	wire [2 : 0] insShort;
	wire [3 : 0] aluCode, insLong;
	wire [7 : 0] Addr, dataAddr;
	wire [15 : 0] inDataA, inDataB, aluData;

	PC pc (
		.clk(clk), .rst(rst), .stop(stop), .pcWR(pcWR), .ifBan(ifBan),
		.jump(dataAddr[7 : 0]), .Addr(Addr)
	);

	INSREG insreg (
		.Addr(Addr),
		.insMode(insMode),
		.insShort(insShort),
		.insLong(insLong),
		.dataAddr(dataAddr)
	);

	ACC acc (
		.clk(clk), .accWR(accWR),
		.inData(aluData),
		.outData(inDataA)
	);

	MEMOR memor (
		.memWR(memWR), .clk(clk),
		.dataAddr(dataAddr[7 : 0]),
		.inData(aluData),
		.outData(inDataB)
	);

	CTRLUNIT cu (
		.insShort(insShort),
		.insLong(insLong),
		.insMode(insMode),
		.stop(stop), .pcWR(pcWR), .accWR(accWR), .memWR(memWR),
		.aluCode(aluCode)
	);

	ALU alu (
		.aluCode(aluCode),
		.inDataA(inDataA), .inDataB(inDataB),
		.ifBan(ifBan),
		.aluData(aluData)
	);

endmodule

Verilog_Folder/CPU/CPU_TB.v
`include "CPU.v"

module CPU_TB;
	reg clk, rst;

	initial begin
		$dumpfile("test.vcd");
		$dumpvars(0, CPU_TB);
		clk = 1;
		rst = 0;

		#1
		rst = ~rst;

		#26
		$stop;
	end

	always @* begin
		if (rst == 1) begin
			#1
			rst = ~rst;
		end
	end

	always #1 begin
		clk = ~clk;
	end

	CPU cpu (
		.clk(clk), .rst(rst)
	);

endmodule

Verilog_Folder/CPU/test.vcd
$date
	Sun Jan 10 20:02:03 2021
$end
$version
	Icarus Verilog
$end
$timescale
	1s
$end
$scope module CPU_TB $end
$var reg 1 ! clk $end
$var reg 1 " rst $end
$scope module cpu $end
$var wire 1 ! clk $end
$var wire 1 " rst $end
$var wire 1 # stop $end
$var wire 1 $ pcWR $end
$var wire 1 % memWR $end
$var wire 3 & insShort [2:0] $end
$var wire 1 ' insMode $end
$var wire 4 ( insLong [3:0] $end
$var wire 16 ) inDataB [15:0] $end
$var wire 16 * inDataA [15:0] $end
$var wire 1 + ifBan $end
$var wire 8 , dataAddr [7:0] $end
$var wire 16 - aluData [15:0] $end
$var wire 4 . aluCode [3:0] $end
$var wire 1 / accWR $end
$var wire 8 0 Addr [7:0] $end
$scope module acc $end
$var wire 1 ! clk $end
$var wire 16 1 outData [15:0] $end
$var wire 16 2 inData [15:0] $end
$var wire 1 / accWR $end
$var reg 16 3 accData [15:0] $end
$upscope $end
$scope module alu $end
$var wire 16 4 inDataA [15:0] $end
$var wire 16 5 inDataB [15:0] $end
$var wire 4 6 aluCode [3:0] $end
$var reg 16 7 aluData [15:0] $end
$var reg 1 + ifBan $end
$upscope $end
$scope module cu $end
$var wire 3 8 insShort [2:0] $end
$var wire 1 ' insMode $end
$var wire 4 9 insLong [3:0] $end
$var reg 1 / accWR $end
$var reg 4 : aluCode [3:0] $end
$var reg 1 % memWR $end
$var reg 1 $ pcWR $end
$var reg 1 # stop $end
$upscope $end
$scope module insreg $end
$var wire 8 ; Addr [7:0] $end
$var reg 8 < dataAddr [7:0] $end
$var reg 12 = ins [11:0] $end
$var reg 4 > insLong [3:0] $end
$var reg 1 ' insMode $end
$var reg 3 ? insShort [2:0] $end
$upscope $end
$scope module memor $end
$var wire 1 ! clk $end
$var wire 8 @ dataAddr [7:0] $end
$var wire 16 A inData [15:0] $end
$var wire 1 % memWR $end
$var wire 16 B outData [15:0] $end
$upscope $end
$scope module pc $end
$var wire 1 ! clk $end
$var wire 1 + ifBan $end
$var wire 8 C jump [7:0] $end
$var wire 1 $ pcWR $end
$var wire 1 " rst $end
$var wire 1 # stop $end
$var reg 8 D Addr [7:0] $end
$upscope $end
$upscope $end
$upscope $end
$enddefinitions $end
#0
$dumpvars
b1 D
b10 C
b1111 B
b1111 A
b10 @
b0 ?
b1000 >
b100000000010 =
b10 <
b1 ;
b100 :
b1000 9
b0 8
b1111 7
b100 6
b1111 5
b0 4
b0 3
b1111 2
b0 1
b1 0
1/
b100 .
b1111 -
b10 ,
0+
b0 *
b1111 )
b1000 (
1'
b0 &
0%
0$
0#
0"
1!
$end
#1
b110 .
b110 6
b110 :
b110000 -
b110000 2
b110000 7
b110000 A
0'
b10 &
b10 8
b10 ?
b0 (
b0 9
b0 >
b110000 )
b110000 5
b110000 B
b1 ,
b1 <
b1 @
b1 C
b1000000001 =
b1111 *
b1111 1
b1111 4
b1111 3
b0 0
b0 ;
b0 D
0!
1"
#2
b100 .
b100 6
b100 :
b11110 -
b11110 2
b11110 7
b11110 A
1'
b0 &
b0 8
b0 ?
b1000 (
b1000 9
b1000 >
b1111 )
b1111 5
b1111 B
b10 ,
b10 <
b10 @
b10 C
b100000000010 =
b1 0
b1 ;
b1 D
0"
1!
#3
b101101 -
b101101 2
b101101 7
b101101 A
b11110 *
b11110 1
b11110 4
b11110 3
0!
#4
b11 .
b11 6
b11 :
b111100 -
b111100 2
b111100 7
b111100 A
b1110 (
b1110 9
b1110 >
b10 )
b10 5
b10 B
b0 ,
b0 <
b0 @
b0 C
b1110 =
b10 0
b10 ;
b10 D
1!
#5
b1111000 -
b1111000 2
b1111000 7
b1111000 A
b111100 *
b111100 1
b111100 4
b111100 3
0!
#6
b11110 -
b11110 2
b11110 7
b11110 A
b10 .
b10 6
b10 :
b1101 (
b1101 9
b1101 >
b1101 =
b11 0
b11 ;
b11 D
1!
#7
b1111 -
b1111 2
b1111 7
b1111 A
b11110 *
b11110 1
b11110 4
b11110 3
0!
#8
b1111111111100001 -
b1111111111100001 2
b1111111111100001 7
b1111111111100001 A
b1 .
b1 6
b1 :
0'
b100 &
b100 8
b100 ?
b0 (
b0 9
b0 >
b100 =
b100 0
b100 ;
b100 D
1!
#9
b11110 -
b11110 2
b11110 7
b11110 A
b1111111111100001 *
b1111111111100001 1
b1111111111100001 4
b1111111111100001 3
0!
#10
b0 -
b0 2
b0 7
b0 A
b0 .
b0 6
b0 :
b11 &
b11 8
b11 ?
b11 =
b101 0
b101 ;
b101 D
1!
#11
b0 *
b0 1
b0 4
b0 3
0!
#12
b1111 -
b1111 2
b1111 7
b1111 A
b110 .
b110 6
b110 :
b10 &
b10 8
b10 ?
b1111 )
b1111 5
b1111 B
b10 ,
b10 <
b10 @
b10 C
b1000000010 =
b110 0
b110 ;
b110 D
1!
#13
b1111 *
b1111 1
b1111 4
b1111 3
0!
#14
b11 .
b11 6
b11 :
b11110 -
b11110 2
b11110 7
b11110 A
1'
b0 &
b0 8
b0 ?
b1110 (
b1110 9
b1110 >
b10 )
b10 5
b10 B
b0 ,
b0 <
b0 @
b0 C
b1110 =
b111 0
b111 ;
b111 D
1!
#15
b111100 -
b111100 2
b111100 7
b111100 A
b11110 *
b11110 1
b11110 4
b11110 3
0!
#16
b1111111111111111 -
b1111111111111111 2
b1111111111111111 7
b1111111111111111 A
b100 .
b100 6
b100 :
b1000 (
b1000 9
b1000 >
b1111111111100001 )
b1111111111100001 5
b1111111111100001 B
b1011 ,
b1011 <
b1011 @
b1011 C
b100000001011 =
b1000 0
b1000 ;
b1000 D
1!
#17
b1111111111100000 -
b1111111111100000 2
b1111111111100000 7
b1111111111100000 A
b1111111111111111 *
b1111111111111111 1
b1111111111111111 4
b1111111111111111 3
0!
#18
0/
1%
b101 .
b101 6
b101 :
b1111111111111111 -
b1111111111111111 2
b1111111111111111 7
b1111111111111111 A
0'
b1 &
b1 8
b1 ?
b0 (
b0 9
b0 >
b1111 )
b1111 5
b1111 B
b10 ,
b10 <
b10 @
b10 C
b100000010 =
b1001 0
b1001 ;
b1001 D
1!
#19
b1111111111111111 )
b1111111111111111 5
b1111111111111111 B
0!
#20
1+
1$
0%
b111 .
b111 6
b111 :
1'
b0 &
b0 8
b0 ?
b1100 (
b1100 9
b1100 >
b110000000010 =
b1010 0
b1010 ;
b1010 D
1!
#21
b1111111111100000 -
b1111111111100000 2
b1111111111100000 7
b1111111111100000 A
0$
1/
b100 .
b100 6
b100 :
b1000 (
b1000 9
b1000 >
b1111111111100001 )
b1111111111100001 5
b1111111111100001 B
b1011 ,
b1011 <
b1011 @
b1011 C
b100000001011 =
b1011 0
b1011 ;
b1011 D
0!
#22
1$
0/
b1111 .
b1111 6
b1111 :
bx -
bx 2
bx 7
bx A
0'
b101 &
b101 8
b101 ?
b0 (
b0 9
b0 >
bx )
bx 5
bx B
b1110 ,
b1110 <
b1110 @
b1110 C
b10100001110 =
b1100 0
b1100 ;
b1100 D
1!
0+
#23
b1111111111100000 -
b1111111111100000 2
b1111111111100000 7
b1111111111100000 A
0$
1/
b100 .
b100 6
b100 :
1'
b0 &
b0 8
b0 ?
b1000 (
b1000 9
b1000 >
b1111111111100001 )
b1111111111100001 5
b1111111111100001 B
b1011 ,
b1011 <
b1011 @
b1011 C
b100000001011 =
b1101 0
b1101 ;
b1101 D
0!
#24
1#
b1111 .
b1111 6
b1111 :
b1 -
b1 2
b1 7
b1 A
b1111 (
b1111 9
b1111 >
b10 )
b10 5
b10 B
b0 ,
b0 <
b0 @
b0 C
b1111 =
b1110 0
b1110 ;
b1110 D
1!
#25
b1 *
b1 1
b1 4
b1 3
0!
